{
    "blogPosts": [
      {
        "uid": "0",
        "title" : "Today's Highlight",
        "text": "Notice the oozy cheese on this delight.",
        "user": "PaperBackWriter",
        "created": "Thu Mar 24 11:55:11 EDT 2022",
        "location": "My House",
        "picID": "placeholder",
        "tags": ["dessert", "breakfast", "cheesy-bacon"],
        "comments": []
      },
      {
        "uid": "1",
        "title": "Second Bottle Today",
        "text": "Only the finest rum for Papa",
        "user": "Ernesto Hemingway",
        "created": "Thu Mar 24 11:58:11 EDT 2022",
        "location": "El Floridita",
        "picID": "placeholder2",
        "tags": ["rum", "daiquiri", "catfood"],
        "comments": []
      }
    ]
}